LinearRegressionMeriem/__init__.py
LinearRegressionMeriem/linear_regression.py
LinearRegressionMeriem-0.1.1.dist-info/LICENSE
LinearRegressionMeriem-0.1.1.dist-info/METADATA
LinearRegressionMeriem-0.1.1.dist-info/WHEEL
LinearRegressionMeriem-0.1.1.dist-info/top_level.txt
LinearRegressionMeriem-0.1.1.dist-info/RECORD
