Metadata-Version: 2.1
Name: LinearRegressionMeriem
Version: 0.1.1
Summary: A simple linear regression model
Home-page: https://github.com/yourusername/LinearRegression
Author: Meriem Terki
Author-email: mrmterki@gmail.com
Classifier: Programming Language :: Python :: 3
Classifier: License :: OSI Approved :: MIT License
Classifier: Operating System :: OS Independent
Requires-Python: >=3.6
License-File: LICENSE
Requires-Dist: numpy
